captainwebhook-0.1.0.dist-info/top_level.txt
captainwebhook-0.1.0.dist-info/entry_points.txt
captainwebhook-0.1.0.dist-info/DESCRIPTION.rst
captainwebhook-0.1.0.dist-info/WHEEL
captainwebhook-0.1.0.dist-info/RECORD
captainwebhook-0.1.0.dist-info/METADATA
captainwebhook-0.1.0.dist-info/metadata.json
captainwebhook/__init__.py
captainwebhook/captainwebhook.py
