Metadata-Version: 2.0
Name: captainwebhook
Version: 0.1.0
Summary: Captain Webhook runs your scripts when it receives a webhook.
Home-page: https://github.com/skorokithakis/captainwebhook
Author: Stavros Korokithakis
Author-email: hi@stavros.io
License: BSD
Keywords: captainwebhook
Platform: UNKNOWN
Classifier: Development Status :: 2 - Pre-Alpha
Classifier: Intended Audience :: Developers
Classifier: License :: OSI Approved :: BSD License
Classifier: Natural Language :: English
Classifier: Programming Language :: Python :: 2
Classifier: Programming Language :: Python :: 2.6
Classifier: Programming Language :: Python :: 2.7
Classifier: Programming Language :: Python :: 3
Classifier: Programming Language :: Python :: 3.3
Classifier: Programming Language :: Python :: 3.4
